pd2wasm/__init__.py
pd2wasm/externals/ExternalClass.py
pd2wasm/externals/Externals.yaml
pd2wasm/externals/__init__.py
pd2wasm/externals/convolve.py
pd2wasm/externals/cyclone.py
pd2wasm/externals/earplug.py
pd2wasm/externals/pdelse.py
pd2wasm/externals/pmpd.py
pd2wasm/externals/timbreID.py
pd2wasm/helpers/__init__.py
pd2wasm/helpers/helpers.py
pd2wasm/index.html
pd2wasm/lib/DynamicLibraries.py
pd2wasm/lib/compiled/libfftw3f.a
pd2wasm/lib/compiled/libpd.a
pd2wasm/lib/libfftw3.py
pd2wasm/pd2wasm.py
pd2wasm/src/enable-threads.js
pd2wasm/src/externals.h
pd2wasm/src/helpers.js
pd2wasm/src/index.html
pd2wasm/src/template.c
pd2wasm/tests/1_SimplePatch/1_SimplePatch.pd
pd2wasm/tests/2_Externals/2_Externals.pd
pd2wasm/tests/3_Dyn_Libs/3_Dyn_Libs.pd
pd2wasm/tests/4_SendData/4_SendData.pd
pd2wasm/tests/runTests.py
pd2wasm-1.1.0.dist-info/LICENSE
pd2wasm-1.1.0.dist-info/METADATA
pd2wasm-1.1.0.dist-info/WHEEL
pd2wasm-1.1.0.dist-info/entry_points.txt
pd2wasm-1.1.0.dist-info/RECORD
