Metadata-Version: 2.1
Name: pd2wasm
Version: 1.1.0
Summary: pd2wasm convert a PureData patch to Wasm file.
Home-page: https://www.charlesneimog.com/PdWebCompiler
Author: Charles K. Neimog
Author-email: charlesneimog@outlook.com
Requires-Python: >=3.10,<4.0
Classifier: Programming Language :: Python :: 3
Classifier: Programming Language :: Python :: 3.10
Classifier: Programming Language :: Python :: 3.11
Requires-Dist: pyyaml (>=6.0.0,<7.0.0)
Requires-Dist: requests (>=2.31.0,<3.0.0)
Project-URL: Documentation, https://www.charlesneimog.github.io/PdWebCompiler
Project-URL: Repository, https://github.com/charlesneimog/PdWebCompiler
